intervention-1.1.0.dist-info/DESCRIPTION.rst
intervention-1.1.0.dist-info/metadata.json
intervention-1.1.0.dist-info/entry_points.txt
intervention-1.1.0.dist-info/WHEEL
intervention-1.1.0.dist-info/METADATA
intervention-1.1.0.dist-info/top_level.txt
intervention-1.1.0.dist-info/RECORD
intervention/darwin.py
intervention/filters.py
intervention/ui.py
intervention/launch.py
intervention/intervention.css
intervention/windows.py
intervention/intervention.ini.example
intervention/settings.py
intervention/__init__.py
