Metadata-Version: 2.0
Name: intervention
Version: 1.1.0
Summary: An intervention to increase intentionality
Home-page: https://github.com/beaugunderson/intervention
Author: Beau Gunderson
Author-email: beau@beaugunderson.com
License: MIT
Keywords: adhd,anxiety,intervention,quantified self
Platform: UNKNOWN
Classifier: Development Status :: 5 - Production/Stable
Classifier: Intended Audience :: End Users/Desktop
Classifier: License :: OSI Approved :: MIT License
Classifier: Operating System :: POSIX
Classifier: Operating System :: Microsoft :: Windows
Classifier: Operating System :: MacOS :: MacOS X
Classifier: Topic :: Utilities
Classifier: Programming Language :: Python :: 3
Classifier: Programming Language :: Python :: 3.4
Requires-Dist: arrow (==0.5.4)
Requires-Dist: PySide (==1.2.2)
Requires-Dist: tini (>=3.0.1)
